{
    "name": "Notificacion",
    "fields": [
        {
            "fieldName": "tituloNotificacion",
            "fieldType": "String"
        },
        {
            "fieldName": "descripcion",
            "fieldType": "String"
        },
        {
            "fieldName": "contenido",
            "fieldType": "String"
        },
        {
            "fieldName": "estado",
            "fieldType": "Integer"
        },
        {
            "fieldName": "fecha",
            "fieldType": "LocalDate"
        },
        {
            "fieldName": "hora",
            "fieldType": "ZonedDateTime"
        },
        {
            "fieldName": "idFraternidad",
            "fieldType": "Integer"
        }
    ],
    "relationships": [
        {
            "relationshipType": "many-to-many",
            "otherEntityName": "fraternidad",
            "otherEntityRelationshipName": "tituloNotificacion",
            "relationshipName": "nombre",
            "otherEntityField": "id",
            "ownerSide": true
        }
    ],
    "changelogDate": "20190510161921",
    "entityTableName": "notificacion",
    "dto": "no",
    "pagination": "no",
    "service": "no",
    "jpaMetamodelFiltering": false,
    "fluentMethods": true,
    "clientRootFolder": "",
    "applications": "*"
}